{
  "id": "3025060",
  "name": "music-app",
  "font_family": "iconfont",
  "css_prefix_text": "icon-",
  "description": "",
  "glyphs": [
    {
      "icon_id": "16648578",
      "name": "循环",
      "font_class": "xunhuan",
      "unicode": "e61f",
      "unicode_decimal": 58911
    },
    {
      "icon_id": "13119206",
      "name": "展开",
      "font_class": "zhankai",
      "unicode": "e7d3",
      "unicode_decimal": 59347
    },
    {
      "icon_id": "688097",
      "name": "上一首 上一个",
      "font_class": "shangyishoushangyige",
      "unicode": "e78a",
      "unicode_decimal": 59274
    },
    {
      "icon_id": "688128",
      "name": "下一个 下一首",
      "font_class": "xiayigexiayishou",
      "unicode": "e7a5",
      "unicode_decimal": 59301
    },
    {
      "icon_id": "5978833",
      "name": "more",
      "font_class": "gengduo",
      "unicode": "e628",
      "unicode_decimal": 58920
    },
    {
      "icon_id": "145472",
      "name": "分享",
      "font_class": "fenxiang",
      "unicode": "e652",
      "unicode_decimal": 58962
    },
    {
      "icon_id": "11352856",
      "name": "30show_多选",
      "font_class": "show_duoxuan",
      "unicode": "e602",
      "unicode_decimal": 58882
    },
    {
      "icon_id": "1581577",
      "name": "聊天",
      "font_class": "liaotian",
      "unicode": "e63c",
      "unicode_decimal": 58940
    },
    {
      "icon_id": "8288890",
      "name": "下载",
      "font_class": "xiazai",
      "unicode": "e856",
      "unicode_decimal": 59478
    },
    {
      "icon_id": "577319",
      "name": "问号",
      "font_class": "wenhao",
      "unicode": "e72d",
      "unicode_decimal": 59181
    },
    {
      "icon_id": "1304897",
      "name": "左箭头",
      "font_class": "zuojiantou",
      "unicode": "e625",
      "unicode_decimal": 58917
    },
    {
      "icon_id": "2815724",
      "name": "视频播放",
      "font_class": "shipinbofang",
      "unicode": "e601",
      "unicode_decimal": 58881
    },
    {
      "icon_id": "5666269",
      "name": "VIP",
      "font_class": "VIP",
      "unicode": "e69d",
      "unicode_decimal": 59037
    },
    {
      "icon_id": "36566",
      "name": "播放",
      "font_class": "bofang1",
      "unicode": "e600",
      "unicode_decimal": 58880
    },
    {
      "icon_id": "4753456",
      "name": "收音机",
      "font_class": "shouyinji",
      "unicode": "e7fa",
      "unicode_decimal": 59386
    },
    {
      "icon_id": "629357",
      "name": "搜索",
      "font_class": "sousuo",
      "unicode": "e651",
      "unicode_decimal": 58961
    },
    {
      "icon_id": "2674474",
      "name": "播放",
      "font_class": "bofang",
      "unicode": "e624",
      "unicode_decimal": 58916
    },
    {
      "icon_id": "2674483",
      "name": "暂停",
      "font_class": "zanting",
      "unicode": "e629",
      "unicode_decimal": 58921
    },
    {
      "icon_id": "5618760",
      "name": "歌单",
      "font_class": "gedan",
      "unicode": "e66a",
      "unicode_decimal": 58986
    },
    {
      "icon_id": "6540838",
      "name": "列表",
      "font_class": "liebiao",
      "unicode": "e60a",
      "unicode_decimal": 58890
    },
    {
      "icon_id": "10340479",
      "name": "排行榜",
      "font_class": "paihangbang",
      "unicode": "e650",
      "unicode_decimal": 58960
    },
    {
      "icon_id": "24732600",
      "name": "推荐",
      "font_class": "tuijian",
      "unicode": "ecb3",
      "unicode_decimal": 60595
    }
  ]
}
